LICENSE
MANIFEST.in
README.md
setup.py
gerrit_cli/__init__.py
gerrit_cli.egg-info/PKG-INFO
gerrit_cli.egg-info/SOURCES.txt
gerrit_cli.egg-info/dependency_links.txt
gerrit_cli.egg-info/entry_points.txt
gerrit_cli.egg-info/not-zip-safe
gerrit_cli.egg-info/requires.txt
gerrit_cli.egg-info/top_level.txt
gerrit_cli/cmd/__init__.py
gerrit_cli/cmd/list.py
gerrit_cli/cmd/main.py